test_petstore_2_api_client/__init__.py
test_petstore_2_api_client/api_client.py
test_petstore_2_api_client/api_response.py
test_petstore_2_api_client/configuration.py
test_petstore_2_api_client/exceptions.py
test_petstore_2_api_client/py.typed
test_petstore_2_api_client/rest.py
test_petstore_2_api_client/api/__init__.py
test_petstore_2_api_client/api/pet_api.py
test_petstore_2_api_client/api/store_api.py
test_petstore_2_api_client/api/user_api.py
test_petstore_2_api_client/models/__init__.py
test_petstore_2_api_client/models/address.py
test_petstore_2_api_client/models/api_response.py
test_petstore_2_api_client/models/category.py
test_petstore_2_api_client/models/customer.py
test_petstore_2_api_client/models/order.py
test_petstore_2_api_client/models/pet.py
test_petstore_2_api_client/models/tag.py
test_petstore_2_api_client/models/user.py
test_petstore_2_api_client-1.0.0.dist-info/METADATA
test_petstore_2_api_client-1.0.0.dist-info/WHEEL
test_petstore_2_api_client-1.0.0.dist-info/top_level.txt
test_petstore_2_api_client-1.0.0.dist-info/RECORD
